sdk/__init__.py
sdk/contextid.py
sdk/sdk.py
sdk/models/__init__.py
sdk/models/operations/__init__.py
sdk/models/operations/addrule.py
sdk/models/operations/evaluaterules.py
sdk/models/operations/getallrules.py
sdk/models/operations/removerule.py
sdk/models/operations/replacerule.py
sdk/models/shared/__init__.py
sdk/models/shared/addruleinput.py
sdk/models/shared/apiaddruleresponse.py
sdk/models/shared/apiallrulesresponse.py
sdk/models/shared/apievaluaterulesresponse.py
sdk/models/shared/apireplaceruleresponse.py
sdk/models/shared/condition.py
sdk/models/shared/conditionbasekey.py
sdk/models/shared/conditionbaseref.py
sdk/models/shared/conditiontype.py
sdk/models/shared/evaluaterulesinput.py
sdk/models/shared/expressionarray.py
sdk/models/shared/modelsevaluationresult.py
sdk/models/shared/modelsrule.py
sdk/models/shared/modelstarget.py
sdk/models/shared/replaceruleinput.py
sdk/utils/__init__.py
sdk/utils/retries.py
sdk/utils/utils.py
brease_sdk-1.3.0.dist-info/LICENSE.md
brease_sdk-1.3.0.dist-info/METADATA
brease_sdk-1.3.0.dist-info/WHEEL
brease_sdk-1.3.0.dist-info/top_level.txt
brease_sdk-1.3.0.dist-info/RECORD
